{"nodes": [{"id": "src_wireviz_wv_bom_py", "label": "wv_bom.py", "file_type": "code", "source_file": "src/wireviz/wv_bom.py", "source_location": "L1"}, {"id": "wv_bom_optional_fields", "label": "optional_fields()", "file_type": "code", "source_file": "src/wireviz/wv_bom.py", "source_location": "L25"}, {"id": "wv_bom_get_additional_component_table", "label": "get_additional_component_table()", "file_type": "code", "source_file": "src/wireviz/wv_bom.py", "source_location": "L31"}, {"id": "wv_bom_get_additional_component_bom", "label": "get_additional_component_bom()", "file_type": "code", "source_file": "src/wireviz/wv_bom.py", "source_location": "L68"}, {"id": "wv_bom_bom_entry_key", "label": "bom_entry_key()", "file_type": "code", "source_file": "src/wireviz/wv_bom.py", "source_location": "L89"}, {"id": "wv_bom_generate_bom", "label": "generate_bom()", "file_type": "code", "source_file": "src/wireviz/wv_bom.py", "source_location": "L98"}, {"id": "wv_bom_get_bom_index", "label": "get_bom_index()", "file_type": "code", "source_file": "src/wireviz/wv_bom.py", "source_location": "L218"}, {"id": "wv_bom_bom_list", "label": "bom_list()", "file_type": "code", "source_file": "src/wireviz/wv_bom.py", "source_location": "L226"}, {"id": "wv_bom_component_table_entry", "label": "component_table_entry()", "file_type": "code", "source_file": "src/wireviz/wv_bom.py", "source_location": "L247"}, {"id": "wv_bom_pn_info_string", "label": "pn_info_string()", "file_type": "code", "source_file": "src/wireviz/wv_bom.py", "source_location": "L278"}, {"id": "wv_bom_index_if_list", "label": "index_if_list()", "file_type": "code", "source_file": "src/wireviz/wv_bom.py", "source_location": "L289"}, {"id": "wv_bom_make_list", "label": "make_list()", "file_type": "code", "source_file": "src/wireviz/wv_bom.py", "source_location": "L294"}, {"id": "wv_bom_make_str", "label": "make_str()", "file_type": "code", "source_file": "src/wireviz/wv_bom.py", "source_location": "L299"}, {"id": "wv_bom_rationale_26", "label": "Return part field values for the optional BOM columns as a dict.", "file_type": "rationale", "source_file": "src/wireviz/wv_bom.py", "source_location": "L26"}, {"id": "wv_bom_rationale_34", "label": "Return a list of diagram node table row strings with additional components.", "file_type": "rationale", "source_file": "src/wireviz/wv_bom.py", "source_location": "L34"}, {"id": "wv_bom_rationale_69", "label": "Return a list of BOM entries with additional components.", "file_type": "rationale", "source_file": "src/wireviz/wv_bom.py", "source_location": "L69"}, {"id": "wv_bom_rationale_90", "label": "Return a tuple of string values from the dict that must be equal to join BOM ent", "file_type": "rationale", "source_file": "src/wireviz/wv_bom.py", "source_location": "L90"}, {"id": "wv_bom_rationale_99", "label": "Return a list of BOM entries generated from the harness.", "file_type": "rationale", "source_file": "src/wireviz/wv_bom.py", "source_location": "L99"}, {"id": "wv_bom_rationale_219", "label": "Return id of BOM entry or raise exception if not found.", "file_type": "rationale", "source_file": "src/wireviz/wv_bom.py", "source_location": "L219"}, {"id": "wv_bom_rationale_227", "label": "Return list of BOM rows as lists of column strings with headings in top row.", "file_type": "rationale", "source_file": "src/wireviz/wv_bom.py", "source_location": "L227"}, {"id": "wv_bom_rationale_258", "label": "Return a diagram node table row string with an additional component.", "file_type": "rationale", "source_file": "src/wireviz/wv_bom.py", "source_location": "L258"}, {"id": "wv_bom_rationale_281", "label": "Return the company name and/or the part number in one single string or None othe", "file_type": "rationale", "source_file": "src/wireviz/wv_bom.py", "source_location": "L281"}, {"id": "wv_bom_rationale_290", "label": "Return the value indexed if it is a list, or simply the value otherwise.", "file_type": "rationale", "source_file": "src/wireviz/wv_bom.py", "source_location": "L290"}, {"id": "wv_bom_rationale_295", "label": "Return value if a list, empty list if None, or single element list otherwise.", "file_type": "rationale", "source_file": "src/wireviz/wv_bom.py", "source_location": "L295"}, {"id": "wv_bom_rationale_300", "label": "Return comma separated elements if a list, empty string if None, or value as a s", "file_type": "rationale", "source_file": "src/wireviz/wv_bom.py", "source_location": "L300"}, {"id": "wv_bom_rationale_129", "label": "# TODO: If category can have other non-empty values than 'bundle', maybe it shou", "file_type": "rationale", "source_file": "src/wireviz/wv_bom.py", "source_location": "L129"}], "edges": [{"source": "src_wireviz_wv_bom_py", "target": "dataclasses", "relation": "imports_from", "confidence": "EXTRACTED", "source_file": "src/wireviz/wv_bom.py", "source_location": "L3", "weight": 1.0}, {"source": "src_wireviz_wv_bom_py", "target": "itertools", "relation": "imports_from", "confidence": "EXTRACTED", "source_file": "src/wireviz/wv_bom.py", "source_location": "L4", "weight": 1.0}, {"source": "src_wireviz_wv_bom_py", "target": "typing", "relation": "imports_from", "confidence": "EXTRACTED", "source_file": "src/wireviz/wv_bom.py", "source_location": "L5", "weight": 1.0}, {"source": "src_wireviz_wv_bom_py", "target": "wireviz_dataclasses", "relation": "imports_from", "confidence": "EXTRACTED", "source_file": "src/wireviz/wv_bom.py", "source_location": "L7", "weight": 1.0}, {"source": "src_wireviz_wv_bom_py", "target": "wireviz_wv_colors", "relation": "imports_from", "confidence": "EXTRACTED", "source_file": "src/wireviz/wv_bom.py", "source_location": "L8", "weight": 1.0}, {"source": "src_wireviz_wv_bom_py", "target": "wireviz_wv_gv_html", "relation": "imports_from", "confidence": "EXTRACTED", "source_file": "src/wireviz/wv_bom.py", "source_location": "L9", "weight": 1.0}, {"source": "src_wireviz_wv_bom_py", "target": "wireviz_wv_helper", "relation": "imports_from", "confidence": "EXTRACTED", "source_file": "src/wireviz/wv_bom.py", "source_location": "L10", "weight": 1.0}, {"source": "src_wireviz_wv_bom_py", "target": "wv_bom_optional_fields", "relation": "contains", "confidence": "EXTRACTED", "source_file": "src/wireviz/wv_bom.py", "source_location": "L25", "weight": 1.0}, {"source": "src_wireviz_wv_bom_py", "target": "wv_bom_get_additional_component_table", "relation": "contains", "confidence": "EXTRACTED", "source_file": "src/wireviz/wv_bom.py", "source_location": "L31", "weight": 1.0}, {"source": "src_wireviz_wv_bom_py", "target": "wv_bom_get_additional_component_bom", "relation": "contains", "confidence": "EXTRACTED", "source_file": "src/wireviz/wv_bom.py", "source_location": "L68", "weight": 1.0}, {"source": "src_wireviz_wv_bom_py", "target": "wv_bom_bom_entry_key", "relation": "contains", "confidence": "EXTRACTED", "source_file": "src/wireviz/wv_bom.py", "source_location": "L89", "weight": 1.0}, {"source": "src_wireviz_wv_bom_py", "target": "wv_bom_generate_bom", "relation": "contains", "confidence": "EXTRACTED", "source_file": "src/wireviz/wv_bom.py", "source_location": "L98", "weight": 1.0}, {"source": "src_wireviz_wv_bom_py", "target": "wv_bom_get_bom_index", "relation": "contains", "confidence": "EXTRACTED", "source_file": "src/wireviz/wv_bom.py", "source_location": "L218", "weight": 1.0}, {"source": "src_wireviz_wv_bom_py", "target": "wv_bom_bom_list", "relation": "contains", "confidence": "EXTRACTED", "source_file": "src/wireviz/wv_bom.py", "source_location": "L226", "weight": 1.0}, {"source": "src_wireviz_wv_bom_py", "target": "wv_bom_component_table_entry", "relation": "contains", "confidence": "EXTRACTED", "source_file": "src/wireviz/wv_bom.py", "source_location": "L247", "weight": 1.0}, {"source": "src_wireviz_wv_bom_py", "target": "wv_bom_pn_info_string", "relation": "contains", "confidence": "EXTRACTED", "source_file": "src/wireviz/wv_bom.py", "source_location": "L278", "weight": 1.0}, {"source": "src_wireviz_wv_bom_py", "target": "wv_bom_index_if_list", "relation": "contains", "confidence": "EXTRACTED", "source_file": "src/wireviz/wv_bom.py", "source_location": "L289", "weight": 1.0}, {"source": "src_wireviz_wv_bom_py", "target": "wv_bom_make_list", "relation": "contains", "confidence": "EXTRACTED", "source_file": "src/wireviz/wv_bom.py", "source_location": "L294", "weight": 1.0}, {"source": "src_wireviz_wv_bom_py", "target": "wv_bom_make_str", "relation": "contains", "confidence": "EXTRACTED", "source_file": "src/wireviz/wv_bom.py", "source_location": "L299", "weight": 1.0}, {"source": "wv_bom_get_additional_component_table", "target": "wv_bom_get_bom_index", "relation": "calls", "confidence": "EXTRACTED", "source_file": "src/wireviz/wv_bom.py", "source_location": "L50", "weight": 1.0}, {"source": "wv_bom_get_additional_component_table", "target": "wv_bom_bom_entry_key", "relation": "calls", "confidence": "EXTRACTED", "source_file": "src/wireviz/wv_bom.py", "source_location": "L52", "weight": 1.0}, {"source": "wv_bom_get_additional_component_table", "target": "wv_bom_component_table_entry", "relation": "calls", "confidence": "EXTRACTED", "source_file": "src/wireviz/wv_bom.py", "source_location": "L55", "weight": 1.0}, {"source": "wv_bom_get_additional_component_table", "target": "wv_bom_optional_fields", "relation": "calls", "confidence": "EXTRACTED", "source_file": "src/wireviz/wv_bom.py", "source_location": "L62", "weight": 1.0}, {"source": "wv_bom_get_additional_component_bom", "target": "wv_bom_optional_fields", "relation": "calls", "confidence": "EXTRACTED", "source_file": "src/wireviz/wv_bom.py", "source_location": "L83", "weight": 1.0}, {"source": "wv_bom_bom_entry_key", "target": "wv_bom_make_str", "relation": "calls", "confidence": "EXTRACTED", "source_file": "src/wireviz/wv_bom.py", "source_location": "L93", "weight": 1.0}, {"source": "wv_bom_generate_bom", "target": "wv_bom_optional_fields", "relation": "calls", "confidence": "EXTRACTED", "source_file": "src/wireviz/wv_bom.py", "source_location": "L121", "weight": 1.0}, {"source": "wv_bom_generate_bom", "target": "wv_bom_get_additional_component_bom", "relation": "calls", "confidence": "EXTRACTED", "source_file": "src/wireviz/wv_bom.py", "source_location": "L126", "weight": 1.0}, {"source": "wv_bom_generate_bom", "target": "wv_bom_index_if_list", "relation": "calls", "confidence": "EXTRACTED", "source_file": "src/wireviz/wv_bom.py", "source_location": "L179", "weight": 1.0}, {"source": "wv_bom_generate_bom", "target": "wv_bom_make_list", "relation": "calls", "confidence": "EXTRACTED", "source_file": "src/wireviz/wv_bom.py", "source_location": "L201", "weight": 1.0}, {"source": "wv_bom_get_bom_index", "target": "wv_bom_bom_entry_key", "relation": "calls", "confidence": "EXTRACTED", "source_file": "src/wireviz/wv_bom.py", "source_location": "L221", "weight": 1.0}, {"source": "wv_bom_bom_list", "target": "wv_bom_make_str", "relation": "calls", "confidence": "EXTRACTED", "source_file": "src/wireviz/wv_bom.py", "source_location": "L243", "weight": 1.0}, {"source": "wv_bom_component_table_entry", "target": "wv_bom_pn_info_string", "relation": "calls", "confidence": "EXTRACTED", "source_file": "src/wireviz/wv_bom.py", "source_location": "L260", "weight": 1.0}, {"source": "wv_bom_make_str", "target": "wv_bom_make_list", "relation": "calls", "confidence": "EXTRACTED", "source_file": "src/wireviz/wv_bom.py", "source_location": "L301", "weight": 1.0}, {"source": "wv_bom_rationale_26", "target": "wv_bom_optional_fields", "relation": "rationale_for", "confidence": "EXTRACTED", "source_file": "src/wireviz/wv_bom.py", "source_location": "L26", "weight": 1.0}, {"source": "wv_bom_rationale_34", "target": "wv_bom_get_additional_component_table", "relation": "rationale_for", "confidence": "EXTRACTED", "source_file": "src/wireviz/wv_bom.py", "source_location": "L34", "weight": 1.0}, {"source": "wv_bom_rationale_69", "target": "wv_bom_get_additional_component_bom", "relation": "rationale_for", "confidence": "EXTRACTED", "source_file": "src/wireviz/wv_bom.py", "source_location": "L69", "weight": 1.0}, {"source": "wv_bom_rationale_90", "target": "wv_bom_bom_entry_key", "relation": "rationale_for", "confidence": "EXTRACTED", "source_file": "src/wireviz/wv_bom.py", "source_location": "L90", "weight": 1.0}, {"source": "wv_bom_rationale_99", "target": "wv_bom_generate_bom", "relation": "rationale_for", "confidence": "EXTRACTED", "source_file": "src/wireviz/wv_bom.py", "source_location": "L99", "weight": 1.0}, {"source": "wv_bom_rationale_219", "target": "wv_bom_get_bom_index", "relation": "rationale_for", "confidence": "EXTRACTED", "source_file": "src/wireviz/wv_bom.py", "source_location": "L219", "weight": 1.0}, {"source": "wv_bom_rationale_227", "target": "wv_bom_bom_list", "relation": "rationale_for", "confidence": "EXTRACTED", "source_file": "src/wireviz/wv_bom.py", "source_location": "L227", "weight": 1.0}, {"source": "wv_bom_rationale_258", "target": "wv_bom_component_table_entry", "relation": "rationale_for", "confidence": "EXTRACTED", "source_file": "src/wireviz/wv_bom.py", "source_location": "L258", "weight": 1.0}, {"source": "wv_bom_rationale_281", "target": "wv_bom_pn_info_string", "relation": "rationale_for", "confidence": "EXTRACTED", "source_file": "src/wireviz/wv_bom.py", "source_location": "L281", "weight": 1.0}, {"source": "wv_bom_rationale_290", "target": "wv_bom_index_if_list", "relation": "rationale_for", "confidence": "EXTRACTED", "source_file": "src/wireviz/wv_bom.py", "source_location": "L290", "weight": 1.0}, {"source": "wv_bom_rationale_295", "target": "wv_bom_make_list", "relation": "rationale_for", "confidence": "EXTRACTED", "source_file": "src/wireviz/wv_bom.py", "source_location": "L295", "weight": 1.0}, {"source": "wv_bom_rationale_300", "target": "wv_bom_make_str", "relation": "rationale_for", "confidence": "EXTRACTED", "source_file": "src/wireviz/wv_bom.py", "source_location": "L300", "weight": 1.0}, {"source": "wv_bom_rationale_129", "target": "src_wireviz_wv_bom_py", "relation": "rationale_for", "confidence": "EXTRACTED", "source_file": "src/wireviz/wv_bom.py", "source_location": "L129", "weight": 1.0}], "raw_calls": [{"caller_nid": "wv_bom_optional_fields", "callee": "asdict", "source_file": "src/wireviz/wv_bom.py", "source_location": "L27"}, {"caller_nid": "wv_bom_optional_fields", "callee": "get", "source_file": "src/wireviz/wv_bom.py", "source_location": "L28"}, {"caller_nid": "wv_bom_get_additional_component_table", "callee": "append", "source_file": "src/wireviz/wv_bom.py", "source_location": "L37"}, {"caller_nid": "wv_bom_get_additional_component_table", "callee": "get_qty_multiplier", "source_file": "src/wireviz/wv_bom.py", "source_location": "L42"}, {"caller_nid": "wv_bom_get_additional_component_table", "callee": "get_qty_multiplier", "source_file": "src/wireviz/wv_bom.py", "source_location": "L45"}, {"caller_nid": "wv_bom_get_additional_component_table", "callee": "bom", "source_file": "src/wireviz/wv_bom.py", "source_location": "L51"}, {"caller_nid": "wv_bom_get_additional_component_table", "callee": "asdict", "source_file": "src/wireviz/wv_bom.py", "source_location": "L52"}, {"caller_nid": "wv_bom_get_additional_component_table", "callee": "append", "source_file": "src/wireviz/wv_bom.py", "source_location": "L54"}, {"caller_nid": "wv_bom_get_additional_component_table", "callee": "rstrip", "source_file": "src/wireviz/wv_bom.py", "source_location": "L56"}, {"caller_nid": "wv_bom_get_additional_component_table", "callee": "append", "source_file": "src/wireviz/wv_bom.py", "source_location": "L60"}, {"caller_nid": "wv_bom_get_additional_component_bom", "callee": "get_qty_multiplier", "source_file": "src/wireviz/wv_bom.py", "source_location": "L75"}, {"caller_nid": "wv_bom_get_additional_component_bom", "callee": "append", "source_file": "src/wireviz/wv_bom.py", "source_location": "L77"}, {"caller_nid": "wv_bom_get_additional_component_bom", "callee": "get_qty_multiplier", "source_file": "src/wireviz/wv_bom.py", "source_location": "L80"}, {"caller_nid": "wv_bom_bom_entry_key", "callee": "tuple", "source_file": "src/wireviz/wv_bom.py", "source_location": "L92"}, {"caller_nid": "wv_bom_bom_entry_key", "callee": "clean_whitespace", "source_file": "src/wireviz/wv_bom.py", "source_location": "L93"}, {"caller_nid": "wv_bom_bom_entry_key", "callee": "get", "source_file": "src/wireviz/wv_bom.py", "source_location": "L93"}, {"caller_nid": "wv_bom_generate_bom", "callee": "values", "source_file": "src/wireviz/wv_bom.py", "source_location": "L104"}, {"caller_nid": "wv_bom_generate_bom", "callee": "translate_color", "source_file": "src/wireviz/wv_bom.py", "source_location": "L112"}, {"caller_nid": "wv_bom_generate_bom", "callee": "append", "source_file": "src/wireviz/wv_bom.py", "source_location": "L117"}, {"caller_nid": "wv_bom_generate_bom", "callee": "extend", "source_file": "src/wireviz/wv_bom.py", "source_location": "L126"}, {"caller_nid": "wv_bom_generate_bom", "callee": "values", "source_file": "src/wireviz/wv_bom.py", "source_location": "L130"}, {"caller_nid": "wv_bom_generate_bom", "callee": "translate_color", "source_file": "src/wireviz/wv_bom.py", "source_location": "L145"}, {"caller_nid": "wv_bom_generate_bom", "callee": "append", "source_file": "src/wireviz/wv_bom.py", "source_location": "L150"}, {"caller_nid": "wv_bom_generate_bom", "callee": "enumerate", "source_file": "src/wireviz/wv_bom.py", "source_location": "L161"}, {"caller_nid": "wv_bom_generate_bom", "callee": "translate_color", "source_file": "src/wireviz/wv_bom.py", "source_location": "L167"}, {"caller_nid": "wv_bom_generate_bom", "callee": "append", "source_file": "src/wireviz/wv_bom.py", "source_location": "L172"}, {"caller_nid": "wv_bom_generate_bom", "callee": "items", "source_file": "src/wireviz/wv_bom.py", "source_location": "L180"}, {"caller_nid": "wv_bom_generate_bom", "callee": "extend", "source_file": "src/wireviz/wv_bom.py", "source_location": "L186"}, {"caller_nid": "wv_bom_generate_bom", "callee": "extend", "source_file": "src/wireviz/wv_bom.py", "source_location": "L189"}, {"caller_nid": "wv_bom_generate_bom", "callee": "clean_whitespace", "source_file": "src/wireviz/wv_bom.py", "source_location": "L193"}, {"caller_nid": "wv_bom_generate_bom", "callee": "items", "source_file": "src/wireviz/wv_bom.py", "source_location": "L193"}, {"caller_nid": "wv_bom_generate_bom", "callee": "groupby", "source_file": "src/wireviz/wv_bom.py", "source_location": "L198"}, {"caller_nid": "wv_bom_generate_bom", "callee": "sorted", "source_file": "src/wireviz/wv_bom.py", "source_location": "L198"}, {"caller_nid": "wv_bom_generate_bom", "callee": "list", "source_file": "src/wireviz/wv_bom.py", "source_location": "L199"}, {"caller_nid": "wv_bom_generate_bom", "callee": "sum", "source_file": "src/wireviz/wv_bom.py", "source_location": "L200"}, {"caller_nid": "wv_bom_generate_bom", "callee": "get", "source_file": "src/wireviz/wv_bom.py", "source_location": "L201"}, {"caller_nid": "wv_bom_generate_bom", "callee": "sum", "source_file": "src/wireviz/wv_bom.py", "source_location": "L203"}, {"caller_nid": "wv_bom_generate_bom", "callee": "get", "source_file": "src/wireviz/wv_bom.py", "source_location": "L203"}, {"caller_nid": "wv_bom_generate_bom", "callee": "append", "source_file": "src/wireviz/wv_bom.py", "source_location": "L204"}, {"caller_nid": "wv_bom_generate_bom", "callee": "int", "source_file": "src/wireviz/wv_bom.py", "source_location": "L207"}, {"caller_nid": "wv_bom_generate_bom", "callee": "is_integer", "source_file": "src/wireviz/wv_bom.py", "source_location": "L208"}, {"caller_nid": "wv_bom_generate_bom", "callee": "float", "source_file": "src/wireviz/wv_bom.py", "source_location": "L208"}, {"caller_nid": "wv_bom_generate_bom", "callee": "round", "source_file": "src/wireviz/wv_bom.py", "source_location": "L209"}, {"caller_nid": "wv_bom_generate_bom", "callee": "sorted", "source_file": "src/wireviz/wv_bom.py", "source_location": "L210"}, {"caller_nid": "wv_bom_generate_bom", "callee": "set", "source_file": "src/wireviz/wv_bom.py", "source_location": "L210"}, {"caller_nid": "wv_bom_generate_bom", "callee": "enumerate", "source_file": "src/wireviz/wv_bom.py", "source_location": "L215"}, {"caller_nid": "wv_bom_get_bom_index", "callee": "Exception", "source_file": "src/wireviz/wv_bom.py", "source_location": "L223"}, {"caller_nid": "wv_bom_get_bom_index", "callee": "join", "source_file": "src/wireviz/wv_bom.py", "source_location": "L223"}, {"caller_nid": "wv_bom_bom_list", "callee": "list", "source_file": "src/wireviz/wv_bom.py", "source_location": "L228"}, {"caller_nid": "wv_bom_bom_list", "callee": "any", "source_file": "src/wireviz/wv_bom.py", "source_location": "L231"}, {"caller_nid": "wv_bom_bom_list", "callee": "get", "source_file": "src/wireviz/wv_bom.py", "source_location": "L231"}, {"caller_nid": "wv_bom_bom_list", "callee": "append", "source_file": "src/wireviz/wv_bom.py", "source_location": "L232"}, {"caller_nid": "wv_bom_bom_list", "callee": "get", "source_file": "src/wireviz/wv_bom.py", "source_location": "L241"}, {"caller_nid": "wv_bom_bom_list", "callee": "capitalize", "source_file": "src/wireviz/wv_bom.py", "source_location": "L241"}, {"caller_nid": "wv_bom_bom_list", "callee": "get", "source_file": "src/wireviz/wv_bom.py", "source_location": "L243"}, {"caller_nid": "wv_bom_component_table_entry", "callee": "any", "source_file": "src/wireviz/wv_bom.py", "source_location": "L268"}, {"caller_nid": "wv_bom_component_table_entry", "callee": "join", "source_file": "src/wireviz/wv_bom.py", "source_location": "L269"}, {"caller_nid": "wv_bom_component_table_entry", "callee": "html_bgcolor_attr", "source_file": "src/wireviz/wv_bom.py", "source_location": "L273"}, {"caller_nid": "wv_bom_component_table_entry", "callee": "html_line_breaks", "source_file": "src/wireviz/wv_bom.py", "source_location": "L274"}, {"caller_nid": "wv_bom_pn_info_string", "callee": "strip", "source_file": "src/wireviz/wv_bom.py", "source_location": "L282"}, {"caller_nid": "wv_bom_pn_info_string", "callee": "str", "source_file": "src/wireviz/wv_bom.py", "source_location": "L282"}, {"caller_nid": "wv_bom_index_if_list", "callee": "isinstance", "source_file": "src/wireviz/wv_bom.py", "source_location": "L291"}, {"caller_nid": "wv_bom_make_list", "callee": "isinstance", "source_file": "src/wireviz/wv_bom.py", "source_location": "L296"}, {"caller_nid": "wv_bom_make_str", "callee": "join", "source_file": "src/wireviz/wv_bom.py", "source_location": "L301"}, {"caller_nid": "wv_bom_make_str", "callee": "str", "source_file": "src/wireviz/wv_bom.py", "source_location": "L301"}]}